qpsychometric/__init__.py
qpsychometric/questionnaire_validator.py
qpsychometric/utils.py
qpsychometric/mental_health/__init__.py
qpsychometric/mental_health/generalized_anxiety_disorder/__init__.py
qpsychometric/mental_health/generalized_anxiety_disorder/gad_qmlm.py
qpsychometric/mental_health/generalized_anxiety_disorder/gad_qmnli.py
qpsychometric/mental_health/patient_health_questionnaire/__init__.py
qpsychometric/mental_health/patient_health_questionnaire/phq_qmlm.py
qpsychometric/mental_health/patient_health_questionnaire/phq_qmnli.py
qpsychometric/mental_health/sense_of_coherence/__init__.py
qpsychometric/mental_health/sense_of_coherence/soc_qmlm.py
qpsychometric/mental_health/sense_of_coherence/soc_qmnli.py
qpsychometric/personality_traits/__init__.py
qpsychometric/personality_traits/big5/__init__.py
qpsychometric/personality_traits/big5/big5_qmlm.py
qpsychometric/personality_traits/big5/big5_qmnli.py
qpsychometric/personality_traits/compassion_scale/__init__.py
qpsychometric/personality_traits/compassion_scale/compassion_scale_qmlm.py
qpsychometric/personality_traits/compassion_scale/compassion_scale_qmnli.py
qpsychometric/personality_traits/short_dark_triad/__init__.py
qpsychometric/personality_traits/short_dark_triad/sd3_qmlm.py
qpsychometric/personality_traits/short_dark_triad/sd3_qmnli.py
qpsychometric/social_biases/__init__.py
qpsychometric/social_biases/ambivalent_sexism_inventory/__init__.py
qpsychometric/social_biases/ambivalent_sexism_inventory/asi_qmlm.py
qpsychometric/social_biases/ambivalent_sexism_inventory/asi_qmnli.py
qpsychometric-1.0.27.dist-info/licenses/LICENSE
qpsychometric-1.0.27.dist-info/METADATA
qpsychometric-1.0.27.dist-info/WHEEL
qpsychometric-1.0.27.dist-info/top_level.txt
qpsychometric-1.0.27.dist-info/RECORD
