Metadata-Version: 2.4
Name: qpsychometric
Version: 1.0.27
Summary: A Python package containing implemented psychometrics for LLMs.
Project-URL: Academic Article, https://openreview.net/pdf/026597881acf1899856edfa5147390a6a60bd3a8.pdf
Classifier: Programming Language :: Python :: 3
Classifier: License :: OSI Approved :: Apache Software License
Classifier: Operating System :: OS Independent
Requires-Python: >=3.8
License-File: LICENSE
Requires-Dist: pandas==2.2.3
Requires-Dist: qlatent>=1.0.11
Requires-Dist: tqdm
Requires-Dist: overrides
Dynamic: classifier
Dynamic: license-file
Dynamic: project-url
Dynamic: requires-dist
Dynamic: requires-python
Dynamic: summary
